augmented_matrix/__init__.py
augmented_matrix/augmented_matrix.py
augmented_matrix-0.10.dist-info/LICENSE
augmented_matrix-0.10.dist-info/METADATA
augmented_matrix-0.10.dist-info/WHEEL
augmented_matrix-0.10.dist-info/top_level.txt
augmented_matrix-0.10.dist-info/RECORD
