Metadata-Version: 2.1
Name: augmented-matrix
Version: 0.10
Summary: A package that solves augmented matrices into reduced echelon forms
Author-email: Yumeng Liu <lym20041026@gmail.com>
License: MIT License
Project-URL: Repository, https://github.com/YumengLiu6044/GaussianElimination
Classifier: Development Status :: 4 - Beta
Classifier: Intended Audience :: Developers
Classifier: Programming Language :: Python :: 3
Classifier: License :: OSI Approved :: MIT License
Classifier: Operating System :: OS Independent
Requires-Python: >=3.9
License-File: LICENSE
Requires-Dist: numpy
